tradingview_utils/__init__.py
tradingview_utils/cookies.py
tradingview_utils/screener.py
tradingview_utils/utils.py
tradingview_utils/websocket.py
tradingview_utils-0.0.1.dist-info/METADATA
tradingview_utils-0.0.1.dist-info/WHEEL
tradingview_utils-0.0.1.dist-info/RECORD
