Metadata-Version: 2.1
Name: tradingview-utils
Version: 0.0.1
Summary: 
Author: Shneor
Author-email: 770elmo@gmail.com
Requires-Python: >=3.11,<4.0
Classifier: Programming Language :: Python :: 3
Classifier: Programming Language :: Python :: 3.11
Classifier: Programming Language :: Python :: 3.12
Requires-Dist: tradingview-screener (>=3.0.0,<4.0.0)
